proj3/ImmediateGenerator.vhdl
-- ImmediateGenerator.vhdl
-- This file defines the immGen entity and its architecture.
-- It is responsible for generating immediate values from instruction codes.

library IEEE;
use IEEE.std_logic_1164.all;
use IEEE.numeric_std.all;

entity ImmediateGenerator is 
    port (
        instruction : in  std_logic_vector(31 downto 0);  -- Input instruction
        immediate   : out signed(31 downto 0)             -- Output immediate value
    );
end entity;

architecture Behavior of ImmediateGenerator is
    -- Define the type for instruction format
    type InstructionFormat is (R_type, I_type, S_type, SB_type, UJ_type, U_type, Unknown_type);

    -- Intermediate signals for various instruction types
    signal I, S, SB, U, UJ, R : signed(31 downto 0);

    -- Detect the instruction type
    signal instrType : InstructionFormat;
    signal opcode    : unsigned(7 downto 0);
    signal funct3    : std_logic_vector(2 downto 0);

begin
    -- Immediate value extraction for different instruction formats
    I  <= resize(signed(instruction(31 downto 20)), 32);
    R  <= (others => '0');
    S  <= resize(signed(instruction(31 downto 25) & instruction(11 downto 7)), 32);
    SB <= resize(signed(instruction(31) & instruction(7) & instruction(30 downto 25) & instruction(11 downto 8) & '0'), 32);
    UJ <= resize(signed(instruction(31) & instruction(19 downto 12) & instruction(20) & instruction(30 downto 21) & '0'), 32);
    U  <= resize(signed(instruction(31 downto 12) & x"000"), 32);

    opcode  <= resize(unsigned(instruction(6 downto 0)), 8);
    funct3  <= instruction(14 downto 12);

    -- Determine instruction type based on opcode
    with opcode select
        instrType <= R_type  when x"33",
                    I_type  when x"03" | x"13" | x"67",
                    S_type  when x"23",
                    SB_type when x"63",
                    U_type  when x"17" | x"37",
                    UJ_type when x"6F",
                    Unknown_type when others;

    -- Output the immediate value based on instruction type
    with instrType select
        immediate <= I  when I_type,
                     S  when S_type,
                     SB when SB_type,
                     U  when U_type,
                     UJ when UJ_type,
                     R  when others;
end Behavior;

trab3/Testbench_ImmediateGenerator.vhdl
-- Testbench_ImmediateGenerator.vhdl
-- This file contains the testbench for the ImmediateGenerator.
-- It tests various instruction types to verify the functionality of ImmediateGenerator.

library IEEE;
use IEEE.std_logic_1164.all;
use IEEE.numeric_std.all;

entity Testbench_ImmediateGenerator is
end entity;

architecture Behavior of Testbench_ImmediateGenerator is
    component ImmediateGenerator
        port (
            instruction : in  std_logic_vector(31 downto 0);
            immediate   : out signed(31 downto 0)
        );
    end component;

    -- Test signals
    signal test_instruction : std_logic_vector(31 downto 0);
    signal test_immediate   : signed(31 downto 0);

begin
    -- Instance of ImmediateGenerator
    uut: ImmediateGenerator port map (instruction => test_instruction, immediate => test_immediate);

    -- Testbench process
    test_process: process
    begin
        -- Test cases with various instruction types
        test_instruction <= X"000002B3"; wait for 10 ns;
        test_instruction <= X"01002283"; wait for 10 ns;
        test_instruction <= X"F9C00313"; wait for 10 ns;
        test_instruction <= X"FFF2C293"; wait for 10 ns;
        test_instruction <= X"16200313"; wait for 10 ns;
        test_instruction <= X"01800067"; wait for 10 ns;
        test_instruction <= X"00002437"; wait for 10 ns;
        test_instruction <= X"02542E23"; wait for 10 ns;
        test_instruction <= X"FE5290E3"; wait for 10 ns;
        test_instruction <= X"00C000EF"; wait for 10 ns;

        wait; -- Terminate the process
    end process;
end Behavior;

trab3/wave.vcd
$date
  Sun Nov 19 15:01:25 2023
$end
$version
  GHDL v0
$end
$timescale
  1 fs
$end
$scope module standard $end
$upscope $end
$scope module std_logic_1164 $end
$upscope $end
$scope module numeric_std $end
$upscope $end
$scope module testbench_immediategenerator $end
$var reg 32 ! test_instruction[31:0] $end
$var reg 32 " test_immediate[31:0] $end
$scope module uut $end
$var reg 32 # instruction[31:0] $end
$var reg 32 $ immediate[31:0] $end
$var reg 32 % i[31:0] $end
$var reg 32 & s[31:0] $end
$var reg 32 ' sb[31:0] $end
$var reg 32 ( u[31:0] $end
$var reg 32 ) uj[31:0] $end
$var reg 32 * r[31:0] $end
$comment instrtype is not handled $end
$var reg 8 + opcode[7:0] $end
$var reg 3 , funct3[2:0] $end
$upscope $end
$upscope $end
$enddefinitions $end
#0
b00000000000000000000001010110011 !
b00000000000000000000000000000000 "
b00000000000000000000001010110011 #
b00000000000000000000000000000000 $
b00000000000000000000000000000000 %
b00000000000000000000000000000101 &
b00000000000000000000100000000100 '
b00000000000000000000000000000000 (
b00000000000000000000000000000000 )
b00000000000000000000000000000000 *
b00110011 +
b000 ,
#10000000
b00000001000000000010001010000011 !
b00000000000000000000000000010000 "
b00000001000000000010001010000011 #
b00000000000000000000000000010000 $
b00000000000000000000000000010000 %
b00000001000000000010000000000000 (
b00000000000000000010000000010000 )
b00000011 +
b010 ,
#20000000
b11111001110000000000001100010011 !
b11111111111111111111111110011100 "
b11111001110000000000001100010011 #
b11111111111111111111111110011100 $
b11111111111111111111111110011100 %
b11111111111111111111111110000110 &
b11111111111111111111011110000110 '
b11111001110000000000000000000000 (
b11111111111100000000011110011100 )
b00010011 +
b000 ,
#30000000
b11111111111100101100001010010011 !
b11111111111111111111111111111111 "
b11111111111100101100001010010011 #
b11111111111111111111111111111111 $
b11111111111111111111111111111111 %
b11111111111111111111111111100101 &
b11111111111111111111111111100100 '
b11111111111100101100000000000000 (
b11111111111100101100111111111110 )
b100 ,
#40000000
b00010110001000000000001100010011 !
b00000000000000000000000101100010 "
b00010110001000000000001100010011 #
b00000000000000000000000101100010 $
b00000000000000000000000101100010 %
b00000000000000000000000101100110 &
b00000000000000000000000101100110 '
b00010110001000000000000000000000 (
b00000000000000000000000101100010 )
b000 ,
#50000000
b00000001100000000000000001100111 !
b00000000000000000000000000011000 "
b00000001100000000000000001100111 #
b00000000000000000000000000011000 $
b00000000000000000000000000011000 %
b00000000000000000000000000000000 &
b00000000000000000000000000000000 '
b00000001100000000000000000000000 (
b00000000000000000000000000011000 )
b01100111 +
#60000000
b00000000000000000010010000110111 !
b00000000000000000010000000000000 "
b00000000000000000010010000110111 #
b00000000000000000010000000000000 $
b00000000000000000000000000000000 %
b00000000000000000000000000001000 &
b00000000000000000000000000001000 '
b00000000000000000010000000000000 (
b00000000000000000010000000000000 )
b00110111 +
b010 ,
#70000000
b00000010010101000010111000100011 !
b00000000000000000000000000111100 "
b00000010010101000010111000100011 #
b00000000000000000000000000111100 $
b00000000000000000000000000100101 %
b00000000000000000000000000111100 &
b00000000000000000000000000111100 '
b00000010010101000010000000000000 (
b00000000000001000010100000100100 )
b00100011 +
#80000000
b11111110010100101001000011100011 !
b11111111111111111111111111100000 "
b11111110010100101001000011100011 #
b11111111111111111111111111100000 $
b11111111111111111111111111100101 %
b11111111111111111111111111100001 &
b11111111111111111111111111100000 '
b11111110010100101001000000000000 (
b11111111111100101001111111100100 )
b01100011 +
b001 ,
#90000000
b00000000110000000000000011101111 !
b00000000000000000000000000001100 "
b00000000110000000000000011101111 #
b00000000000000000000000000001100 $
b00000000000000000000000000001100 %
b00000000000000000000000000000001 &
b00000000000000000000100000000000 '
b00000000110000000000000000000000 (
b00000000000000000000000000001100 )
b01101111 +
b000 ,
