proj5/XREG.vhdl
library IEEE;
use IEEE.STD_LOGIC_1164.ALL;
use IEEE.NUMERIC_STD.ALL;

entity XREG is
    Port ( clk   : in  STD_LOGIC;
           wren  : in  STD_LOGIC;
           rs1   : in  STD_LOGIC_VECTOR (4 downto 0);
           rs2   : in  STD_LOGIC_VECTOR (4 downto 0);
           rd    : in  STD_LOGIC_VECTOR (4 downto 0);
           data  : in  STD_LOGIC_VECTOR (31 downto 0);
           ro1   : out STD_LOGIC_VECTOR (31 downto 0);
           ro2   : out STD_LOGIC_VECTOR (31 downto 0)
         );
end XREG;

architecture Behavioral of XREG is
    type reg_array is array (0 to 31) of STD_LOGIC_VECTOR (31 downto 0);
    signal registers : reg_array := (others => (others => '0'));
begin
    process(clk)
    begin
        if rising_edge(clk) then
            if wren = '1' and to_integer(unsigned(rd)) /= 0 then
                registers(to_integer(unsigned(rd))) <= data;
            end if;

            ro1 <= registers(to_integer(unsigned(rs1)));
            ro2 <= registers(to_integer(unsigned(rs2)));
        end if;
    end process;
end Behavioral;

proj5/Testbench_XREG.vhdl
library IEEE;
use IEEE.STD_LOGIC_1164.ALL;
use IEEE.NUMERIC_STD.ALL; 

entity XREG_TB is
end XREG_TB;

architecture behavior of XREG_TB is 
    component XREG
    Port ( clk   : in  STD_LOGIC;
           wren  : in  STD_LOGIC;
           rs1   : in  STD_LOGIC_VECTOR (4 downto 0);
           rs2   : in  STD_LOGIC_VECTOR (4 downto 0);
           rd    : in  STD_LOGIC_VECTOR (4 downto 0);
           data  : in  STD_LOGIC_VECTOR (31 downto 0);
           ro1   : out STD_LOGIC_VECTOR (31 downto 0);
           ro2   : out STD_LOGIC_VECTOR (31 downto 0)
         );
    end component;

    --Inputs
    signal clk   : STD_LOGIC := '0';
    signal wren  : STD_LOGIC := '0';
    signal rs1   : STD_LOGIC_VECTOR (4 downto 0) := (others => '0');
    signal rs2   : STD_LOGIC_VECTOR (4 downto 0) := (others => '0');
    signal rd    : STD_LOGIC_VECTOR (4 downto 0) := (others => '0');
    signal data  : STD_LOGIC_VECTOR (31 downto 0) := (others => '0');

    --Outputs
    signal ro1   : STD_LOGIC_VECTOR (31 downto 0);
    signal ro2   : STD_LOGIC_VECTOR (31 downto 0);

    -- Clock period definitions
    constant clk_period : time := 10 ns;

begin
    -- Instantiate the Unit Under Test (UUT)
    uut: XREG Port Map (
          clk => clk,
          wren => wren,
          rs1 => rs1,
          rs2 => rs2,
          rd => rd,
          data => data,
          ro1 => ro1,
          ro2 => ro2
        );

    -- Clock process definitions
    clk_process :process
    begin
        clk <= '0';
        wait for clk_period/2;
        clk <= '1';
        wait for clk_period/2;
    end process;

    -- Test process
    stim_proc: process
        variable allZero : STD_LOGIC_VECTOR (31 downto 0) := (others => '0');
    begin		
        -- Test case 1: Write and read from register
        rd <= "00001"; -- Register 1
        data <= X"12345678";
        wren <= '1';
        wait for clk_period*10;
        wren <= '0';
        rs1 <= "00001"; -- Read from register 1
        wait for clk_period*10;
        assert (ro1 = X"12345678") report "Write and read from register test failed" severity failure;
        report "Write and read from register test passed" severity note;
        
        -- Test case 2: Ensure register 0 is constant
        rd <= "00000"; -- Register 0 (constant)
        data <= X"FFFFFFFF";
        wren <= '1';
        wait for clk_period*10;
        wren <= '0';
        rs1 <= "00000"; -- Read from register 0
        wait for clk_period*10;
        assert (ro2 = X"00000000") report "Ensure register 0 is constant test failed" severity failure;
        report "Ensure register 0 is constant test passed" severity note;

        -- Read from unwritten registers
        rs1 <= "00010"; -- Unwritten register
        rs2 <= "00011"; -- Another unwritten register
        wait for clk_period*10;
        assert (ro1 = allZero) report "Unwritten register test failed - rs1" severity failure;
        report "Unwritten register test passed - rs1" severity note;

        assert (ro2 = allZero) report "Unwritten register test failed - rs2" severity failure;
        report "Unwritten register test passed - rs2" severity note;

        -- Multiple writes and reads
        -- Write to registers
        for i in 1 to 5 loop
            rd <= std_logic_vector(to_unsigned(i, 5));
            data <= std_logic_vector(to_unsigned(i*111, 32)); -- Some arbitrary data
            wren <= '1';
            wait for clk_period*10;
            wren <= '0';
            wait for clk_period*10;
        end loop;

        -- Read from registers and check values
        for i in 1 to 5 loop
            rs1 <= std_logic_vector(to_unsigned(i, 5));
            wait for clk_period*10;
            assert (ro1 = std_logic_vector(to_unsigned(i*111, 32))) report "Multiple writes/reads test failed for register" & integer'image(i) severity failure;
            report "Multiple writes/reads test passed - register " & integer'image(i) severity note;
        end loop;

        -- Simultaneous read from two registers
        rd <= "00100"; -- Register 4
        data <= X"A5A5A5A5";
        wren <= '1';
        wait for clk_period*10;
        wren <= '0';

        rd <= "00101"; -- Register 5
        data <= X"5A5A5A5A";
        wren <= '1';
        wait for clk_period*10;
        wren <= '0';

        rs1 <= "00100"; -- Read from register 4
        rs2 <= "00101"; -- Read from register 5
        wait for clk_period*10;
        assert (ro1 = X"A5A5A5A5") report "Simultaneous read test failed - register 4" severity failure;
        report "Simultaneous read test passed - register 4" severity note;

        assert (ro2 = X"5A5A5A5A") report "Simultaneous read test failed - register 5" severity failure;
        report "Simultaneous read test passed - register 5" severity note;

        wait;
    end process;
end behavior;

proj5/wave.vcd
$date
  Thu Nov 30 16:58:04 2023
$end
$version
  GHDL v0
$end
$timescale
  1 fs
$end
$scope module standard $end
$upscope $end
$scope module textio $end
$upscope $end
$scope module std_logic_1164 $end
$upscope $end
$scope module numeric_std $end
$upscope $end
$scope module xreg_tb $end
$var reg 1 ! clk $end
$var reg 1 " wren $end
$var reg 5 # rs1[4:0] $end
$var reg 5 $ rs2[4:0] $end
$var reg 5 % rd[4:0] $end
$var reg 32 & data[31:0] $end
$var reg 32 ' ro1[31:0] $end
$var reg 32 ( ro2[31:0] $end
$scope module uut $end
$var reg 1 ) clk $end
$var reg 1 * wren $end
$var reg 5 + rs1[4:0] $end
$var reg 5 , rs2[4:0] $end
$var reg 5 - rd[4:0] $end
$var reg 32 . data[31:0] $end
$var reg 32 / ro1[31:0] $end
$var reg 32 0 ro2[31:0] $end
$comment registers is not handled $end
$upscope $end
$upscope $end
$enddefinitions $end
#0
0!
1"
b00000 #
b00000 $
b00001 %
b00010010001101000101011001111000 &
bUUUUUUUUUUUUUUUUUUUUUUUUUUUUUUUU '
bUUUUUUUUUUUUUUUUUUUUUUUUUUUUUUUU (
0)
1*
b00000 +
b00000 ,
b00001 -
b00010010001101000101011001111000 .
bUUUUUUUUUUUUUUUUUUUUUUUUUUUUUUUU /
bUUUUUUUUUUUUUUUUUUUUUUUUUUUUUUUU 0
#5000000
1!
b00000000000000000000000000000000 '
b00000000000000000000000000000000 (
1)
b00000000000000000000000000000000 /
b00000000000000000000000000000000 0
#10000000
0!
0)
#15000000
1!
1)
#20000000
0!
0)
#25000000
1!
1)
#30000000
0!
0)
#35000000
1!
1)
#40000000
0!
0)
#45000000
1!
1)
#50000000
0!
0)
#55000000
1!
1)
#60000000
0!
0)
#65000000
1!
1)
#70000000
0!
0)
#75000000
1!
1)
#80000000
0!
0)
#85000000
1!
1)
#90000000
0!
0)
#95000000
1!
1)
#100000000
0!
0"
b00001 #
0)
0*
b00001 +
#105000000
1!
b00010010001101000101011001111000 '
1)
b00010010001101000101011001111000 /
#110000000
0!
0)
#115000000
1!
1)
#120000000
0!
0)
#125000000
1!
1)
#130000000
0!
0)
#135000000
1!
1)
#140000000
0!
0)
#145000000
1!
1)
#150000000
0!
0)
#155000000
1!
1)
#160000000
0!
0)
#165000000
1!
1)
#170000000
0!
0)
#175000000
1!
1)
#180000000
0!
0)
#185000000
1!
1)
#190000000
0!
0)
#195000000
1!
1)
#200000000
0!
1"
b00000 %
b11111111111111111111111111111111 &
0)
1*
b00000 -
b11111111111111111111111111111111 .
#205000000
1!
1)
#210000000
0!
0)
#215000000
1!
1)
#220000000
0!
0)
#225000000
1!
1)
#230000000
0!
0)
#235000000
1!
1)
#240000000
0!
0)
#245000000
1!
1)
#250000000
0!
0)
#255000000
1!
1)
#260000000
0!
0)
#265000000
1!
1)
#270000000
0!
0)
#275000000
1!
1)
#280000000
0!
0)
#285000000
1!
1)
#290000000
0!
0)
#295000000
1!
1)
#300000000
0!
0"
b00000 #
0)
0*
b00000 +
#305000000
1!
b00000000000000000000000000000000 '
1)
b00000000000000000000000000000000 /
#310000000
0!
0)
#315000000
1!
1)
#320000000
0!
0)
#325000000
1!
1)
#330000000
0!
0)
#335000000
1!
1)
#340000000
0!
0)
#345000000
1!
1)
#350000000
0!
0)
#355000000
1!
1)
#360000000
0!
0)
#365000000
1!
1)
#370000000
0!
0)
#375000000
1!
1)
#380000000
0!
0)
#385000000
1!
1)
#390000000
0!
0)
#395000000
1!
1)
#400000000
0!
b00010 #
b00011 $
0)
b00010 +
b00011 ,
#405000000
1!
1)
#410000000
0!
0)
#415000000
1!
1)
#420000000
0!
0)
#425000000
1!
1)
#430000000
0!
0)
#435000000
1!
1)
#440000000
0!
0)
#445000000
1!
1)
#450000000
0!
0)
#455000000
1!
1)
#460000000
0!
0)
#465000000
1!
1)
#470000000
0!
0)
#475000000
1!
1)
#480000000
0!
0)
#485000000
1!
1)
#490000000
0!
0)
#495000000
1!
1)
#500000000
0!
1"
b00001 %
b00000000000000000000000001101111 &
0)
1*
b00001 -
b00000000000000000000000001101111 .
#505000000
1!
1)
#510000000
0!
0)
#515000000
1!
1)
#520000000
0!
0)
#525000000
1!
1)
#530000000
0!
0)
#535000000
1!
1)
#540000000
0!
0)
#545000000
1!
1)
#550000000
0!
0)
#555000000
1!
1)
#560000000
0!
0)
#565000000
1!
1)
#570000000
0!
0)
#575000000
1!
1)
#580000000
0!
0)
#585000000
1!
1)
#590000000
0!
0)
#595000000
1!
1)
#600000000
0!
0"
0)
0*
#605000000
1!
1)
#610000000
0!
0)
#615000000
1!
1)
#620000000
0!
0)
#625000000
1!
1)
#630000000
0!
0)
#635000000
1!
1)
#640000000
0!
0)
#645000000
1!
1)
#650000000
0!
0)
#655000000
1!
1)
#660000000
0!
0)
#665000000
1!
1)
#670000000
0!
0)
#675000000
1!
1)
#680000000
0!
0)
#685000000
1!
1)
#690000000
0!
0)
#695000000
1!
1)
#700000000
0!
1"
b00010 %
b00000000000000000000000011011110 &
0)
1*
b00010 -
b00000000000000000000000011011110 .
#705000000
1!
1)
#710000000
0!
0)
#715000000
1!
b00000000000000000000000011011110 '
1)
b00000000000000000000000011011110 /
#720000000
0!
0)
#725000000
1!
1)
#730000000
0!
0)
#735000000
1!
1)
#740000000
0!
0)
#745000000
1!
1)
#750000000
0!
0)
#755000000
1!
1)
#760000000
0!
0)
#765000000
1!
1)
#770000000
0!
0)
#775000000
1!
1)
#780000000
0!
0)
#785000000
1!
1)
#790000000
0!
0)
#795000000
1!
1)
#800000000
0!
0"
0)
0*
#805000000
1!
1)
#810000000
0!
0)
#815000000
1!
1)
#820000000
0!
0)
#825000000
1!
1)
#830000000
0!
0)
#835000000
1!
1)
#840000000
0!
0)
#845000000
1!
1)
#850000000
0!
0)
#855000000
1!
1)
#860000000
0!
0)
#865000000
1!
1)
#870000000
0!
0)
#875000000
1!
1)
#880000000
0!
0)
#885000000
1!
1)
#890000000
0!
0)
#895000000
1!
1)
#900000000
0!
1"
b00011 %
b00000000000000000000000101001101 &
0)
1*
b00011 -
b00000000000000000000000101001101 .
#905000000
1!
1)
#910000000
0!
0)
#915000000
1!
b00000000000000000000000101001101 (
1)
b00000000000000000000000101001101 0
#920000000
0!
0)
#925000000
1!
1)
#930000000
0!
0)
#935000000
1!
1)
#940000000
0!
0)
#945000000
1!
1)
#950000000
0!
0)
#955000000
1!
1)
#960000000
0!
0)
#965000000
1!
1)
#970000000
0!
0)
#975000000
1!
1)
#980000000
0!
0)
#985000000
1!
1)
#990000000
0!
0)
#995000000
1!
1)
#1000000000
0!
0"
0)
0*
#1005000000
1!
1)
#1010000000
0!
0)
#1015000000
1!
1)
#1020000000
0!
0)
#1025000000
1!
1)
#1030000000
0!
0)
#1035000000
1!
1)
#1040000000
0!
0)
#1045000000
1!
1)
#1050000000
0!
0)
#1055000000
1!
1)
#1060000000
0!
0)
#1065000000
1!
1)
#1070000000
0!
0)
#1075000000
1!
1)
#1080000000
0!
0)
#1085000000
1!
1)
#1090000000
0!
0)
#1095000000
1!
1)
#1100000000
0!
1"
b00100 %
b00000000000000000000000110111100 &
0)
1*
b00100 -
b00000000000000000000000110111100 .
#1105000000
1!
1)
#1110000000
0!
0)
#1115000000
1!
1)
#1120000000
0!
0)
#1125000000
1!
1)
#1130000000
0!
0)
#1135000000
1!
1)
#1140000000
0!
0)
#1145000000
1!
1)
#1150000000
0!
0)
#1155000000
1!
1)
#1160000000
0!
0)
#1165000000
1!
1)
#1170000000
0!
0)
#1175000000
1!
1)
#1180000000
0!
0)
#1185000000
1!
1)
#1190000000
0!
0)
#1195000000
1!
1)
#1200000000
0!
0"
0)
0*
#1205000000
1!
1)
#1210000000
0!
0)
#1215000000
1!
1)
#1220000000
0!
0)
#1225000000
1!
1)
#1230000000
0!
0)
#1235000000
1!
1)
#1240000000
0!
0)
#1245000000
1!
1)
#1250000000
0!
0)
#1255000000
1!
1)
#1260000000
0!
0)
#1265000000
1!
1)
#1270000000
0!
0)
#1275000000
1!
1)
#1280000000
0!
0)
#1285000000
1!
1)
#1290000000
0!
0)
#1295000000
1!
1)
#1300000000
0!
1"
b00101 %
b00000000000000000000001000101011 &
0)
1*
b00101 -
b00000000000000000000001000101011 .
#1305000000
1!
1)
#1310000000
0!
0)
#1315000000
1!
1)
#1320000000
0!
0)
#1325000000
1!
1)
#1330000000
0!
0)
#1335000000
1!
1)
#1340000000
0!
0)
#1345000000
1!
1)
#1350000000
0!
0)
#1355000000
1!
1)
#1360000000
0!
0)
#1365000000
1!
1)
#1370000000
0!
0)
#1375000000
1!
1)
#1380000000
0!
0)
#1385000000
1!
1)
#1390000000
0!
0)
#1395000000
1!
1)
#1400000000
0!
0"
0)
0*
#1405000000
1!
1)
#1410000000
0!
0)
#1415000000
1!
1)
#1420000000
0!
0)
#1425000000
1!
1)
#1430000000
0!
0)
#1435000000
1!
1)
#1440000000
0!
0)
#1445000000
1!
1)
#1450000000
0!
0)
#1455000000
1!
1)
#1460000000
0!
0)
#1465000000
1!
1)
#1470000000
0!
0)
#1475000000
1!
1)
#1480000000
0!
0)
#1485000000
1!
1)
#1490000000
0!
0)
#1495000000
1!
1)
#1500000000
0!
b00001 #
0)
b00001 +
#1505000000
1!
b00000000000000000000000001101111 '
1)
b00000000000000000000000001101111 /
#1510000000
0!
0)
#1515000000
1!
1)
#1520000000
0!
0)
#1525000000
1!
1)
#1530000000
0!
0)
#1535000000
1!
1)
#1540000000
0!
0)
#1545000000
1!
1)
#1550000000
0!
0)
#1555000000
1!
1)
#1560000000
0!
0)
#1565000000
1!
1)
#1570000000
0!
0)
#1575000000
1!
1)
#1580000000
0!
0)
#1585000000
1!
1)
#1590000000
0!
0)
#1595000000
1!
1)
#1600000000
0!
b00010 #
0)
b00010 +
#1605000000
1!
b00000000000000000000000011011110 '
1)
b00000000000000000000000011011110 /
#1610000000
0!
0)
#1615000000
1!
1)
#1620000000
0!
0)
#1625000000
1!
1)
#1630000000
0!
0)
#1635000000
1!
1)
#1640000000
0!
0)
#1645000000
1!
1)
#1650000000
0!
0)
#1655000000
1!
1)
#1660000000
0!
0)
#1665000000
1!
1)
#1670000000
0!
0)
#1675000000
1!
1)
#1680000000
0!
0)
#1685000000
1!
1)
#1690000000
0!
0)
#1695000000
1!
1)
#1700000000
0!
b00011 #
0)
b00011 +
#1705000000
1!
b00000000000000000000000101001101 '
1)
b00000000000000000000000101001101 /
#1710000000
0!
0)
#1715000000
1!
1)
#1720000000
0!
0)
#1725000000
1!
1)
#1730000000
0!
0)
#1735000000
1!
1)
#1740000000
0!
0)
#1745000000
1!
1)
#1750000000
0!
0)
#1755000000
1!
1)
#1760000000
0!
0)
#1765000000
1!
1)
#1770000000
0!
0)
#1775000000
1!
1)
#1780000000
0!
0)
#1785000000
1!
1)
#1790000000
0!
0)
#1795000000
1!
1)
#1800000000
0!
b00100 #
0)
b00100 +
#1805000000
1!
b00000000000000000000000110111100 '
1)
b00000000000000000000000110111100 /
#1810000000
0!
0)
#1815000000
1!
1)
#1820000000
0!
0)
#1825000000
1!
1)
#1830000000
0!
0)
#1835000000
1!
1)
#1840000000
0!
0)
#1845000000
1!
1)
#1850000000
0!
0)
#1855000000
1!
1)
#1860000000
0!
0)
#1865000000
1!
1)
#1870000000
0!
0)
#1875000000
1!
1)
#1880000000
0!
0)
#1885000000
1!
1)
#1890000000
0!
0)
#1895000000
1!
1)
#1900000000
0!
b00101 #
0)
b00101 +
#1905000000
1!
b00000000000000000000001000101011 '
1)
b00000000000000000000001000101011 /
#1910000000
0!
0)
#1915000000
1!
1)
#1920000000
0!
0)
#1925000000
1!
1)
#1930000000
0!
0)
#1935000000
1!
1)
#1940000000
0!
0)
#1945000000
1!
1)
#1950000000
0!
0)
#1955000000
1!
1)
#1960000000
0!
0)
#1965000000
1!
1)
#1970000000
0!
0)
#1975000000
1!
1)
#1980000000
0!
0)
#1985000000
1!
1)
#1990000000
0!
0)
#1995000000
1!
1)
#2000000000
0!
1"
b00100 %
b10100101101001011010010110100101 &
0)
1*
b00100 -
b10100101101001011010010110100101 .
#2005000000
1!
1)
#2010000000
0!
0)
#2015000000
1!
1)
#2020000000
0!
0)
#2025000000
1!
1)
#2030000000
0!
0)
#2035000000
1!
1)
#2040000000
0!
0)
#2045000000
1!
1)
#2050000000
0!
0)
#2055000000
1!
1)
#2060000000
0!
0)
#2065000000
1!
1)
#2070000000
0!
0)
#2075000000
1!
1)
#2080000000
0!
0)
#2085000000
1!
1)
#2090000000
0!
0)
#2095000000
1!
1)
#2100000000
0!
b00101 %
b01011010010110100101101001011010 &
0)
b00101 -
b01011010010110100101101001011010 .
#2105000000
1!
1)
#2110000000
0!
0)
#2115000000
1!
b01011010010110100101101001011010 '
1)
b01011010010110100101101001011010 /
#2120000000
0!
0)
#2125000000
1!
1)
#2130000000
0!
0)
#2135000000
1!
1)
#2140000000
0!
0)
#2145000000
1!
1)
#2150000000
0!
0)
#2155000000
1!
1)
#2160000000
0!
0)
#2165000000
1!
1)
#2170000000
0!
0)
#2175000000
1!
1)
#2180000000
0!
0)
#2185000000
1!
1)
#2190000000
0!
0)
#2195000000
1!
1)
#2200000000
0!
0"
b00100 #
b00101 $
0)
0*
b00100 +
b00101 ,
#2205000000
1!
b10100101101001011010010110100101 '
b01011010010110100101101001011010 (
1)
b10100101101001011010010110100101 /
b01011010010110100101101001011010 0
#2210000000
0!
0)
#2215000000
1!
1)
#2220000000
0!
0)
#2225000000
1!
1)
#2230000000
0!
0)
#2235000000
1!
1)
#2240000000
0!
0)
#2245000000
1!
1)
#2250000000
0!
0)
#2255000000
1!
1)
#2260000000
0!
0)
#2265000000
1!
1)
#2270000000
0!
0)
#2275000000
1!
1)
#2280000000
0!
0)
#2285000000
1!
1)
#2290000000
0!
0)
#2295000000
1!
1)
#2300000000
0!
1"
b00001 %
b00010010001101000101011001111000 &
0)
1*
b00001 -
b00010010001101000101011001111000 .
#2305000000
1!
1)
#2310000000
0!
0)
#2315000000
1!
1)
#2320000000
0!
0)
#2325000000
1!
1)
#2330000000
0!
0)
#2335000000
1!
1)
#2340000000
0!
0)
#2345000000
1!
1)
#2350000000
0!
0)
#2355000000
1!
1)
#2360000000
0!
0)
#2365000000
1!
1)
#2370000000
0!
0)
#2375000000
1!
1)
#2380000000
0!
0)
#2385000000
1!
1)
#2390000000
0!
0)
#2395000000
1!
1)
#2400000000
0!
0"
b00001 #
0)
0*
b00001 +
#2405000000
1!
b00010010001101000101011001111000 '
1)
b00010010001101000101011001111000 /
#2410000000
0!
0)
#2415000000
1!
1)
#2420000000
0!
0)
#2425000000
1!
1)
#2430000000
0!
0)
#2435000000
1!
1)
#2440000000
0!
0)
#2445000000
1!
1)
#2450000000
0!
0)
#2455000000
1!
1)
#2460000000
0!
0)
#2465000000
1!
1)
#2470000000
0!
0)
#2475000000
1!
1)
#2480000000
0!
0)
#2485000000
1!
1)
#2490000000
0!
0)
#2495000000
1!
1)
#2500000000
0!
1"
b00000 %
b11111111111111111111111111111111 &
0)
1*
b00000 -
b11111111111111111111111111111111 .
#2505000000
1!
1)
#2510000000
0!
0)
#2515000000
1!
1)
#2520000000
0!
0)
#2525000000
1!
1)
#2530000000
0!
0)
#2535000000
1!
1)
#2540000000
0!
0)
#2545000000
1!
1)
#2550000000
0!
0)
#2555000000
1!
1)
#2560000000
0!
0)
#2565000000
1!
1)
#2570000000
0!
0)
#2575000000
1!
1)
#2580000000
0!
0)
#2585000000
1!
1)
#2590000000
0!
0)
#2595000000
1!
1)
#2600000000
0!
0"
b00000 #
0)
0*
b00000 +
#2605000000
1!
b00000000000000000000000000000000 '
1)
b00000000000000000000000000000000 /
