proj5/src/XREG.vhdl
library IEEE;
use IEEE.STD_LOGIC_1164.ALL;
use IEEE.NUMERIC_STD.ALL;

entity XREG is
    Port ( clk   : in  STD_LOGIC;
           wren  : in  STD_LOGIC;
           rs1   : in  STD_LOGIC_VECTOR (4 downto 0);
           rs2   : in  STD_LOGIC_VECTOR (4 downto 0);
           rd    : in  STD_LOGIC_VECTOR (4 downto 0);
           data  : in  STD_LOGIC_VECTOR (31 downto 0);
           ro1   : out STD_LOGIC_VECTOR (31 downto 0);
           ro2   : out STD_LOGIC_VECTOR (31 downto 0)
         );
end XREG;

architecture Behavioral of XREG is
    type reg_array is array (0 to 31) of STD_LOGIC_VECTOR (31 downto 0);
    signal registers : reg_array := (others => (others => '0'));
begin
    process(clk)
    begin
        if rising_edge(clk) then
            if wren = '1' and to_integer(unsigned(rd)) >= 0 and to_integer(unsigned(rd)) < 32 then
                registers(to_integer(unsigned(rd))) <= data;
            end if;

            ro1 <= registers(to_integer(unsigned(rs1)));
            ro2 <= registers(to_integer(unsigned(rs2)));
        end if;
    end process;
end Behavioral;

proj5/Testbench_XREG.vhdl
library IEEE;
use IEEE.STD_LOGIC_1164.ALL;
use IEEE.NUMERIC_STD.ALL; 

entity XREG_TB is
end XREG_TB;

architecture behavior of XREG_TB is 
    component XREG
    Port ( clk   : in  STD_LOGIC;
           wren  : in  STD_LOGIC;
           rs1   : in  STD_LOGIC_VECTOR (4 downto 0);
           rs2   : in  STD_LOGIC_VECTOR (4 downto 0);
           rd    : in  STD_LOGIC_VECTOR (4 downto 0);
           data  : in  STD_LOGIC_VECTOR (31 downto 0);
           ro1   : out STD_LOGIC_VECTOR (31 downto 0);
           ro2   : out STD_LOGIC_VECTOR (31 downto 0)
         );
    end component;

    --Inputs
    signal clk   : STD_LOGIC := '0';
    signal wren  : STD_LOGIC := '0';
    signal rs1   : STD_LOGIC_VECTOR (4 downto 0) := (others => '0');
    signal rs2   : STD_LOGIC_VECTOR (4 downto 0) := (others => '0');
    signal rd    : STD_LOGIC_VECTOR (4 downto 0) := (others => '0');
    signal data  : STD_LOGIC_VECTOR (31 downto 0) := (others => '0');

    --Outputs
    signal ro1   : STD_LOGIC_VECTOR (31 downto 0);
    signal ro2   : STD_LOGIC_VECTOR (31 downto 0);

    -- Clock period definitions
    constant clk_period : time := 10 ns;

    -- Test control
    signal test_finished : boolean := false;

begin
    -- Instantiate the Unit Under Test (UUT)
    uut: XREG Port Map (
          clk => clk,
          wren => wren,
          rs1 => rs1,
          rs2 => rs2,
          rd => rd,
          data => data,
          ro1 => ro1,
          ro2 => ro2
        );

    -- Clock process definitions
    clk_process : process
    begin
        while not test_finished loop
            clk <= '0';
            wait for clk_period/2;
            clk <= '1';
            wait for clk_period/2;
        end loop;
        wait;  -- Terminate the process after the test is finished
    end process;

    -- Test process
    stim_proc: process
    begin
        -- Initialize
        wren <= '0';
        wait for clk_period;

        -- Write to register
        rd <= "00001"; -- Register 1
        data <= X"12345678";
        wren <= '1';
        wait for clk_period;
        wren <= '0';
        wait for clk_period; -- Ensure a full clock cycle before reading

        -- Read from register
        rs1 <= "00001"; -- Read from register 1
        wait for clk_period;
        assert (ro1 = X"12345678") report "Write and read from register test failed" severity failure;
        report "Write and read from register test passed" severity note;

        -- Ensure register 0 is constant
        -- Write to register 0 (should have no effect)
        rd <= "00000"; -- Register 0 (constant)
        data <= X"FFFFFFFF";
        wren <= '1';
        wait for clk_period;
        wren <= '0';
        wait for clk_period; -- Ensure a full clock cycle before reading

        -- Read from register 0 (should still be zero)
        rs1 <= "00000"; -- Read from register 0
        wait for clk_period;
        assert (ro1 = X"00000000") report "Ensure register 0 is constant test failed" severity failure;
        report "Ensure register 0 is constant test passed" severity note;

        -- Read from unwritten registers
        rs1 <= "00010"; -- Unwritten register
        rs2 <= "00011"; -- Another unwritten register
        wait for clk_period;
        assert (ro1 = X"00000000") report "Unwritten register test failed - rs1" severity failure;
        report "Unwritten register test passed - rs1" severity note;

        assert (ro2 = X"00000000") report "Unwritten register test failed - rs2" severity failure;
        report "Unwritten register test passed - rs2" severity note;

        -- Multiple writes and reads
        -- Write to registers
        for i in 1 to 5 loop
            rd <= std_logic_vector(to_unsigned(i, 5));
            data <= std_logic_vector(to_unsigned(i*111, 32)); -- Some arbitrary data
            wren <= '1';
            wait for clk_period;
            wren <= '0';
            wait for clk_period;
        end loop;

        -- Read from registers and check values
        for i in 1 to 5 loop
            rs1 <= std_logic_vector(to_unsigned(i, 5));
            wait for clk_period;
            assert (ro1 = std_logic_vector(to_unsigned(i*111, 32))) report "Multiple writes/reads test failed for register" & integer'image(i) severity failure;
            report "Multiple writes/reads test passed - register " & integer'image(i) severity note;
        end loop;

        -- Simultaneous read from two registers
        rd <= "00100"; -- Register 4
        data <= X"A5A5A5A5";
        wren <= '1';
        wait for clk_period;
        wren <= '0';

        rd <= "00101"; -- Register 5
        data <= X"5A5A5A5A";
        wren <= '1';
        wait for clk_period;
        wren <= '0';

        rs1 <= "00100"; -- Read from register 4
        rs2 <= "00101"; -- Read from register 5
        wait for clk_period;
        assert (ro1 = X"A5A5A5A5") report "Simultaneous read test failed - register 4" severity failure;
        report "Simultaneous read test passed - register 4" severity note;

        assert (ro2 = X"5A5A5A5A") report "Simultaneous read test failed - register 5" severity failure;
        report "Simultaneous read test passed - register 5" severity note;

        -- End of test
        test_finished <= true;
        wait;
    end process;
end behavior;

proj5/src/wave.vcd
$date
  Thu Nov 30 17:20:11 2023
$end
$version
  GHDL v0
$end
$timescale
  1 fs
$end
$scope module standard $end
$upscope $end
$scope module textio $end
$upscope $end
$scope module std_logic_1164 $end
$upscope $end
$scope module numeric_std $end
$upscope $end
$scope module xreg_tb $end
$var reg 1 ! clk $end
$var reg 1 " wren $end
$var reg 5 # rs1[4:0] $end
$var reg 5 $ rs2[4:0] $end
$var reg 5 % rd[4:0] $end
$var reg 32 & data[31:0] $end
$var reg 32 ' ro1[31:0] $end
$var reg 32 ( ro2[31:0] $end
$var reg 1 ) test_finished $end
$scope module uut $end
$var reg 1 * clk $end
$var reg 1 + wren $end
$var reg 5 , rs1[4:0] $end
$var reg 5 - rs2[4:0] $end
$var reg 5 . rd[4:0] $end
$var reg 32 / data[31:0] $end
$var reg 32 0 ro1[31:0] $end
$var reg 32 1 ro2[31:0] $end
$comment registers is not handled $end
$upscope $end
$upscope $end
$enddefinitions $end
#0
0!
0"
b00000 #
b00000 $
b00000 %
b00000000000000000000000000000000 &
bUUUUUUUUUUUUUUUUUUUUUUUUUUUUUUUU '
bUUUUUUUUUUUUUUUUUUUUUUUUUUUUUUUU (
0)
0*
0+
b00000 ,
b00000 -
b00000 .
b00000000000000000000000000000000 /
bUUUUUUUUUUUUUUUUUUUUUUUUUUUUUUUU 0
bUUUUUUUUUUUUUUUUUUUUUUUUUUUUUUUU 1
#5000000
1!
b00000000000000000000000000000000 '
b00000000000000000000000000000000 (
1*
b00000000000000000000000000000000 0
b00000000000000000000000000000000 1
#10000000
0!
1"
b00001 %
b00010010001101000101011001111000 &
0*
1+
b00001 .
b00010010001101000101011001111000 /
#15000000
1!
1*
#20000000
0!
0"
0*
0+
#25000000
1!
1*
#30000000
0!
b00001 #
0*
b00001 ,
#35000000
1!
b00010010001101000101011001111000 '
1*
b00010010001101000101011001111000 0
#40000000
0!
1"
b00000 %
b11111111111111111111111111111111 &
0*
1+
b00000 .
b11111111111111111111111111111111 /
#45000000
1!
1*
#50000000
0!
0"
0*
0+
#55000000
1!
1*
#60000000
0!
b00000 #
0*
b00000 ,
#65000000
1!
b00000000000000000000000000000000 '
1*
b00000000000000000000000000000000 0
#70000000
0!
b00010 #
b00011 $
0*
b00010 ,
b00011 -
#75000000
1!
1*
#80000000
0!
1"
b00001 %
b00000000000000000000000001101111 &
0*
1+
b00001 .
b00000000000000000000000001101111 /
#85000000
1!
1*
#90000000
0!
0"
0*
0+
#95000000
1!
1*
#100000000
0!
1"
b00010 %
b00000000000000000000000011011110 &
0*
1+
b00010 .
b00000000000000000000000011011110 /
#105000000
1!
1*
#110000000
0!
0"
0*
0+
#115000000
1!
b00000000000000000000000011011110 '
1*
b00000000000000000000000011011110 0
#120000000
0!
1"
b00011 %
b00000000000000000000000101001101 &
0*
1+
b00011 .
b00000000000000000000000101001101 /
#125000000
1!
1*
#130000000
0!
0"
0*
0+
#135000000
1!
b00000000000000000000000101001101 (
1*
b00000000000000000000000101001101 1
#140000000
0!
1"
b00100 %
b00000000000000000000000110111100 &
0*
1+
b00100 .
b00000000000000000000000110111100 /
#145000000
1!
1*
#150000000
0!
0"
0*
0+
#155000000
1!
1*
#160000000
0!
1"
b00101 %
b00000000000000000000001000101011 &
0*
1+
b00101 .
b00000000000000000000001000101011 /
#165000000
1!
1*
#170000000
0!
0"
0*
0+
#175000000
1!
1*
#180000000
0!
b00001 #
0*
b00001 ,
#185000000
1!
b00000000000000000000000001101111 '
1*
b00000000000000000000000001101111 0
#190000000
0!
b00010 #
0*
b00010 ,
#195000000
1!
b00000000000000000000000011011110 '
1*
b00000000000000000000000011011110 0
#200000000
0!
b00011 #
0*
b00011 ,
#205000000
1!
b00000000000000000000000101001101 '
1*
b00000000000000000000000101001101 0
#210000000
0!
b00100 #
0*
b00100 ,
#215000000
1!
b00000000000000000000000110111100 '
1*
b00000000000000000000000110111100 0
#220000000
0!
b00101 #
0*
b00101 ,
#225000000
1!
b00000000000000000000001000101011 '
1*
b00000000000000000000001000101011 0
#230000000
0!
1"
b00100 %
b10100101101001011010010110100101 &
0*
1+
b00100 .
b10100101101001011010010110100101 /
#235000000
1!
1*
#240000000
0!
b00101 %
b01011010010110100101101001011010 &
0*
b00101 .
b01011010010110100101101001011010 /
#245000000
1!
1*
#250000000
0!
0"
b00100 #
b00101 $
0*
0+
b00100 ,
b00101 -
#255000000
1!
b10100101101001011010010110100101 '
b01011010010110100101101001011010 (
1*
b10100101101001011010010110100101 0
b01011010010110100101101001011010 1
#260000000
0!
1)
0*
