proj4/aluRV32.vhdl
LIBRARY ieee;
USE ieee.std_logic_1164.ALL;
USE ieee.numeric_std.ALL;

ENTITY AluRV32 IS
    GENERIC (WSIZE : NATURAL := 32);
    PORT (
        opcode : IN  std_logic_vector(3 DOWNTO 0);
        A, B   : IN  std_logic_vector(WSIZE-1 DOWNTO 0);
        Z      : OUT std_logic_vector(WSIZE-1 DOWNTO 0);
        zero   : OUT std_logic
    );
END AluRV32;

ARCHITECTURE behavior OF AluRV32 IS
BEGIN
    PROCESS (opcode, A, B)
    BEGIN
        CASE opcode IS
            WHEN "0000" => -- ADD
                Z <= std_logic_vector(unsigned(A) + unsigned(B));
            WHEN "0001" => -- SUB
                Z <= std_logic_vector(unsigned(A) - unsigned(B));
            WHEN "0010" => -- AND
                Z <= A AND B;
            WHEN "0011" => -- OR
                Z <= A OR B;
            WHEN "0100" => -- XOR
                Z <= A XOR B;
            WHEN "0101" => -- SLL
                Z <= std_logic_vector(shift_left(unsigned(A), to_integer(unsigned(B))));
            WHEN "0110" => -- SRL
                Z <= std_logic_vector(shift_right(unsigned(A), to_integer(unsigned(B))));
            WHEN "0111" => -- SRA
                Z <= std_logic_vector(shift_right(signed(A), to_integer(unsigned(B))));
            WHEN "1000" => -- SLT
                Z <= (others => '0');
                Z(0) <= '1' WHEN signed(A) < signed(B) ELSE '0';
            WHEN "1001" => -- SLTU
                Z <= (others => '0');
                Z(0) <= '1' WHEN unsigned(A) < unsigned(B) ELSE '0';
            WHEN "1010" => -- SGE
                Z <= (others => '0');
                Z(0) <= '1' WHEN signed(A) >= signed(B) ELSE '0';
            WHEN "1011" => -- SGEU
                Z <= (others => '0');
                Z(0) <= '1' WHEN unsigned(A) >= unsigned(B) ELSE '0';
            WHEN "1100" => -- SEQ
                Z <= '1' WHEN A = B ELSE '0';
            WHEN "1101" => -- SNE
                Z <= '1' WHEN A /= B ELSE '0';
            WHEN OTHERS =>
                Z <= (others => '0');
        END CASE;
        zero <= '1' WHEN Z = (others => '0') ELSE '0';
    END PROCESS;
END behavior;

proj4/Testbench_aluRV32.vhdl
LIBRARY ieee;
USE ieee.std_logic_1164.all;
USE ieee.numeric_std.all;

ENTITY Testbench_AluRV32 IS
END Testbench_AluRV32;

ARCHITECTURE tb_arch OF Testbench_AluRV32 IS
    SIGNAL opcode: std_logic_vector(3 DOWNTO 0);
    SIGNAL A, B, Z: std_logic_vector(31 DOWNTO 0);
    SIGNAL zero: std_logic;

    -- Declaration of the ALU component
    COMPONENT AluRV32
        PORT (
            opcode : IN  std_logic_vector(3 DOWNTO 0);
            A, B   : IN  std_logic_vector(31 DOWNTO 0);
            Z      : OUT std_logic_vector(31 DOWNTO 0);
            zero   : OUT std_logic
        );
    END COMPONENT;

    -- Instantiation of the ALU
    BEGIN
        ULA: AluRV32 PORT MAP (opcode => opcode, A => A, B => B, Z => Z, zero => zero);

        -- Stimulus process
        PROCESS
        BEGIN
            -- ADD
            opcode <= "0000"; -- ADD
            A <= std_logic_vector(to_signed(5, 32));
            B <= std_logic_vector(to_signed(3, 32));
            WAIT FOR 10 ns;
            ASSERT Z = std_logic_vector(to_signed(8, 32)) REPORT "ADD failed - Z" SEVERITY FAILURE;
            ASSERT zero = '0' REPORT "ADD failed - zero" SEVERITY FAILURE;
            REPORT "ADD OK";

            -- ADD (Zero)
            opcode <= "0000"; -- ADD
            A <= std_logic_vector(to_signed(0, 32));
            B <= std_logic_vector(to_signed(0, 32));
            WAIT FOR 10 ns;          
            ASSERT Z = std_logic_vector(to_signed(0, 32)) REPORT "ADD (Zero) failed - Z" SEVERITY FAILURE;
            ASSERT zero = '1' REPORT "ADD (Zero) failed - zero" SEVERITY FAILURE;
            REPORT "ADD (Zero) OK";

            -- SUB
            opcode <= "0001"; -- SUB
            A <= std_logic_vector(to_signed(10, 32));
            B <= std_logic_vector(to_signed(4, 32));
            WAIT FOR 10 ns;    
            ASSERT Z = std_logic_vector(to_signed(6, 32)) REPORT "SUB failed - Z" SEVERITY FAILURE;
            ASSERT zero = '0' REPORT "SUB failed - zero" SEVERITY FAILURE;
            REPORT "SUB OK";

            -- AND
            opcode <= "0010"; -- AND
            A <= std_logic_vector(to_signed(15, 32));
            B <= std_logic_vector(to_signed(7, 32));
            WAIT FOR 10 ns;       
            ASSERT Z = std_logic_vector(to_signed(7, 32)) REPORT "AND failed - Z" SEVERITY FAILURE;
            ASSERT zero = '0' REPORT "AND failed - zero" SEVERITY FAILURE;
            REPORT "AND OK";

            -- OR
            opcode <= "0011"; -- OR
            A <= std_logic_vector(to_signed(12, 32));
            B <= std_logic_vector(to_signed(5, 32));
            WAIT FOR 10 ns;    
            ASSERT Z = std_logic_vector(to_signed(13, 32)) REPORT "OR failed - Z" SEVERITY FAILURE;
            ASSERT zero = '0' REPORT "OR failed - zero" SEVERITY FAILURE;
            REPORT "OR OK";

            -- XOR
            opcode <= "0100"; -- XOR
            A <= std_logic_vector(to_signed(9, 32));
            B <= std_logic_vector(to_signed(3, 32));
            WAIT FOR 10 ns;          
            ASSERT Z = std_logic_vector(to_signed(10, 32)) REPORT "XOR failed - Z" SEVERITY FAILURE;
            ASSERT zero = '0' REPORT "XOR failed - zero" SEVERITY FAILURE;
            REPORT "XOR OK";

            -- SLL
            opcode <= "0101"; -- SLL
            A <= std_logic_vector(to_signed(8, 32));
            B <= std_logic_vector(to_signed(2, 32)); -- Shift amount
            WAIT FOR 10 ns;
            ASSERT Z = std_logic_vector(to_signed(32, 32)) REPORT "SLL failed - Z" SEVERITY FAILURE;
            ASSERT zero = '0' REPORT "SLL failed - zero" SEVERITY FAILURE;
            REPORT "SLL OK";

            -- SRL
            opcode <= "0110"; -- SRL
            A <= std_logic_vector(to_signed(16, 32));
            B <= std_logic_vector(to_signed(1, 32)); -- Shift amount
            WAIT FOR 10 ns;
            ASSERT Z = std_logic_vector(to_signed(8, 32)) REPORT "SRL failed - Z" SEVERITY FAILURE;
            ASSERT zero = '0' REPORT "SRL failed - zero" SEVERITY FAILURE;
            REPORT "SRL OK";

            -- SRA
            opcode <= "0111"; -- SRA
            A <= std_logic_vector(to_signed(32, 32));
            B <= std_logic_vector(to_signed(2, 32)); -- Shift amount
            WAIT FOR 10 ns;
            ASSERT Z = std_logic_vector(to_signed(8, 32)) REPORT "SRA failed - Z" SEVERITY FAILURE;
            ASSERT zero = '0' REPORT "SRA failed - zero" SEVERITY FAILURE;
            REPORT "SRA OK";

            -- SLT
            opcode <= "1000"; -- SLT
            A <= std_logic_vector(to_signed(5, 32));
            B <= std_logic_vector(to_signed(7, 32));
            WAIT FOR 10 ns;
            ASSERT Z = std_logic_vector(to_signed(1, 32)) REPORT "SLT failed - Z" SEVERITY FAILURE;
            ASSERT zero = '0' REPORT "SLT failed - zero" SEVERITY FAILURE;
            REPORT "SLT OK";

            -- SLTU
            opcode <= "1001"; -- SLTU
            A <= std_logic_vector(to_signed(6, 32));
            B <= std_logic_vector(to_signed(8, 32));
            WAIT FOR 10 ns;
            ASSERT Z = std_logic_vector(to_signed(1, 32)) REPORT "SLTU failed - Z" SEVERITY FAILURE;
            ASSERT zero = '0' REPORT "SLTU failed - zero" SEVERITY FAILURE;
            REPORT "SLTU OK";

            -- SGE
            opcode <= "1010"; -- SGE
            A <= std_logic_vector(to_signed(9, 32));
            B <= std_logic_vector(to_signed(3, 32));
            WAIT FOR 10 ns;
            ASSERT Z = std_logic_vector(to_signed(1, 32)) REPORT "SGE failed - Z" SEVERITY FAILURE;
            ASSERT zero = '0' REPORT "SGE failed - zero" SEVERITY FAILURE;
            REPORT "SGE OK";

            -- SGEU
            opcode <= "1011"; -- SGEU
            A <= std_logic_vector(to_signed(10, 32));
            B <= std_logic_vector(to_signed(5, 32));
            WAIT FOR 10 ns;
            ASSERT Z = std_logic_vector(to_signed(1, 32)) REPORT "SGEU failed - Z" SEVERITY FAILURE;
            ASSERT zero = '0' REPORT "SGEU failed - zero" SEVERITY FAILURE;
            REPORT "SGEU OK";

            -- SEQ
            opcode <= "1100"; -- SEQ
            A <= std_logic_vector(to_signed(4, 32));
            B <= std_logic_vector(to_signed(4, 32));
            WAIT FOR 10 ns;
            ASSERT Z = std_logic_vector(to_signed(1, 32)) REPORT "SEQ failed - Z" SEVERITY FAILURE;
            ASSERT zero = '0' REPORT "SEQ failed- zero" SEVERITY FAILURE;
            REPORT "SEQ OK";

            -- SEQ (Zero)
            opcode <= "1100"; -- SEQ
            A <= std_logic_vector(to_signed(2, 32));
            B <= std_logic_vector(to_signed(4, 32));
            WAIT FOR 10 ns;
            ASSERT Z = std_logic_vector(to_signed(0, 32)) REPORT "SEQ (Zero) failed - Z" SEVERITY FAILURE;
            ASSERT zero = '1' REPORT "SEQ (Zero) failed- zero" SEVERITY FAILURE;
            REPORT "SEQ (Zero) OK";

            -- SNE
            opcode <= "1101"; -- SNE
            A <= std_logic_vector(to_signed(5, 32));
            B <= std_logic_vector(to_signed(6, 32));
            WAIT FOR 10 ns;
            ASSERT Z = std_logic_vector(to_signed(1, 32)) REPORT "SNE failed - Z" SEVERITY FAILURE;
            ASSERT zero = '0' REPORT "SNE failed - zero" SEVERITY FAILURE;
            REPORT "SNE OK";

            WAIT;
        END PROCESS;
END tb_arch;

proj4/wave.vcd
$date
  Sun Nov 26 21:24:42 2023
$end
$version
  GHDL v0
$end
$timescale
  1 fs
$end
$scope module standard $end
$upscope $end
$scope module textio $end
$upscope $end
$scope module std_logic_1164 $end
$upscope $end
$scope module numeric_std $end
$upscope $end
$scope module testbench_alurv32 $end
$var reg 4 ! opcode[3:0] $end
$var reg 32 " a[31:0] $end
$var reg 32 # b[31:0] $end
$var reg 32 $ z[31:0] $end
$var reg 1 % zero $end
$scope module ula $end
$var reg 4 & opcode[3:0] $end
$var reg 32 ' a[31:0] $end
$var reg 32 ( b[31:0] $end
$var reg 32 ) z[31:0] $end
$var reg 1 * zero $end
$upscope $end
$upscope $end
$enddefinitions $end
#0
b0000 !
b00000000000000000000000000000101 "
b00000000000000000000000000000011 #
b00000000000000000000000000001000 $
0%
b0000 &
b00000000000000000000000000000101 '
b00000000000000000000000000000011 (
b00000000000000000000000000001000 )
0*
#10000000
b00000000000000000000000000000000 "
b00000000000000000000000000000000 #
b00000000000000000000000000000000 $
1%
b00000000000000000000000000000000 '
b00000000000000000000000000000000 (
b00000000000000000000000000000000 )
1*
#20000000
b0001 !
b00000000000000000000000000001010 "
b00000000000000000000000000000100 #
b00000000000000000000000000000110 $
0%
b0001 &
b00000000000000000000000000001010 '
b00000000000000000000000000000100 (
b00000000000000000000000000000110 )
0*
#30000000
b0010 !
b00000000000000000000000000001111 "
b00000000000000000000000000000111 #
b00000000000000000000000000000111 $
b0010 &
b00000000000000000000000000001111 '
b00000000000000000000000000000111 (
b00000000000000000000000000000111 )
#40000000
b0011 !
b00000000000000000000000000001100 "
b00000000000000000000000000000101 #
b00000000000000000000000000001101 $
b0011 &
b00000000000000000000000000001100 '
b00000000000000000000000000000101 (
b00000000000000000000000000001101 )
#50000000
b0100 !
b00000000000000000000000000001001 "
b00000000000000000000000000000011 #
b00000000000000000000000000001010 $
b0100 &
b00000000000000000000000000001001 '
b00000000000000000000000000000011 (
b00000000000000000000000000001010 )
#60000000
b0101 !
b00000000000000000000000000001000 "
b00000000000000000000000000000010 #
b00000000000000000000000000100000 $
b0101 &
b00000000000000000000000000001000 '
b00000000000000000000000000000010 (
b00000000000000000000000000100000 )
#70000000
b0110 !
b00000000000000000000000000010000 "
b00000000000000000000000000000001 #
b00000000000000000000000000001000 $
b0110 &
b00000000000000000000000000010000 '
b00000000000000000000000000000001 (
b00000000000000000000000000001000 )
#80000000
b0111 !
b00000000000000000000000000100000 "
b00000000000000000000000000000010 #
b0111 &
b00000000000000000000000000100000 '
b00000000000000000000000000000010 (
#90000000
b1000 !
b00000000000000000000000000000101 "
b00000000000000000000000000000111 #
b00000000000000000000000000000001 $
b1000 &
b00000000000000000000000000000101 '
b00000000000000000000000000000111 (
b00000000000000000000000000000001 )
#100000000
b1001 !
b00000000000000000000000000000110 "
b00000000000000000000000000001000 #
b1001 &
b00000000000000000000000000000110 '
b00000000000000000000000000001000 (
b00000000000000000000000000000001 )
#110000000
b1010 !
b00000000000000000000000000001001 "
b00000000000000000000000000000011 #
b1010 &
b00000000000000000000000000001001 '
b00000000000000000000000000000011 (
b00000000000000000000000000000001 )
#120000000
b1011 !
b00000000000000000000000000001010 "
b00000000000000000000000000000101 #
b1011 &
b00000000000000000000000000001010 '
b00000000000000000000000000000101 (
b00000000000000000000000000000001 )
#130000000
b1100 !
b00000000000000000000000000000100 "
b00000000000000000000000000000100 #
b1100 &
b00000000000000000000000000000100 '
b00000000000000000000000000000100 (
b00000000000000000000000000000001 )
#140000000
b00000000000000000000000000000010 "
b00000000000000000000000000000000 $
1%
b00000000000000000000000000000010 '
b00000000000000000000000000000000 )
1*
#150000000
b1101 !
b00000000000000000000000000000101 "
b00000000000000000000000000000110 #
b00000000000000000000000000000001 $
0%
b1101 &
b00000000000000000000000000000101 '
b00000000000000000000000000000110 (
b00000000000000000000000000000001 )
0*
