proj6/ROM_RV32.vhdl
-- ROM module for RISC-V unicore
library ieee;
use ieee.std_logic_1164.all;
use ieee.numeric_std.all;
use std.textio.all;

entity ROM_RV32 is
    port (
        address : in std_logic_vector(7 downto 0);
        dataout : out std_logic_vector(31 downto 0)
    );
end entity ROM_RV32;

architecture RTL of ROM_RV32 is

    -- Constants for ROM depth and width
    constant rom_depth : natural := 256;
    constant rom_width : natural := 32;

    -- Define the ROM type
    type rom_type is array (0 to rom_depth - 1) of std_logic_vector(rom_width - 1 downto 0);

    -- Function to initialize ROM from a hex file
    impure function init_rom_from_hex return rom_type is
        file hex_file : text open read_mode is "rom_content_hex.txt"; -- Adjust path as needed
        variable line_v : line;
        variable hex_value : std_logic_vector(31 downto 0);
        variable rom_contents : rom_type;
    begin
        for i in 0 to rom_depth - 1 loop
            if not endfile(hex_file) then
                readline(hex_file, line_v);
                hread(line_v, hex_value);
                rom_contents(i) := hex_value;
            else
                rom_contents(i) := (others => '0'); -- Fill remaining with 0s if file ends
            end if;
        end loop;
        return rom_contents;
    end function;

    -- Initialize ROM with data from file
    signal mem : rom_type := init_rom_from_hex;

begin
    -- Read operation for ROM
    process(address)
    begin
        dataout <= mem(to_integer(unsigned(address)));
    end process;

end RTL;

proj6/src/RAM_RV32.vhdl
-- RAM module for RISC-V unicore
library ieee;
use ieee.std_logic_1164.all;
use ieee.numeric_std.all;

entity RAM_RV32 is
    port (
        clock   : in std_logic;
        we      : in std_logic;
        address : in std_logic_vector(7 downto 0);
        datain  : in std_logic_vector(31 downto 0) := (others => '0'); -- Default value (Avoid undefined value)
        dataout : out std_logic_vector(31 downto 0)
    );
end entity RAM_RV32;

architecture RTL of RAM_RV32 is
    type mem_type is array (0 to 255) of std_logic_vector(31 downto 0);
    signal mem : mem_type := (others => (others => '0'));
    signal read_address : std_logic_vector(7 downto 0) := (others => '0');
begin
    -- Read and write process
    process(clock)
    begin
        if rising_edge(clock) then
            if we = '1' then
                -- Write operation
                mem(to_integer(unsigned(address))) <= datain;
            else
                -- Read operation
                read_address <= address;
            end if;
        end if;
    end process;

    -- Data output
    dataout <= mem(to_integer(unsigned(read_address)));

end RTL;

proj6/src/Testbench_RAM_ROM.vhdl
library ieee;
use ieee.std_logic_1164.all;
use ieee.numeric_std.all;

entity testbench_ram_rom is
end entity testbench_ram_rom;

architecture behavior of testbench_ram_rom is
    -- Component declaration for the RAM and ROM
    component RAM_RV32
        port (
            clock   : in std_logic;
            we      : in std_logic;
            address : in std_logic_vector(7 downto 0);
            datain  : in std_logic_vector(31 downto 0);
            dataout : out std_logic_vector(31 downto 0)
        );
    end component;

    component ROM_RV32
        port (
            address : in std_logic_vector(7 downto 0);
            dataout : out std_logic_vector(31 downto 0)
        );
    end component;

    -- Signals for interfacing with the RAM and ROM
    signal clock   : std_logic := '0';
    signal we      : std_logic := '0'; 
    signal address : std_logic_vector(7 downto 0) := (others => '0'); 
    signal datain  : std_logic_vector(31 downto 0) := (others => '0'); 
    signal dataout_ram : std_logic_vector(31 downto 0) := (others => '0'); 
    signal dataout_rom : std_logic_vector(31 downto 0) := (others => '0'); 
    signal test_finished : boolean := false;

begin
    -- Instantiate the RAM and ROM
    uut_ram: component RAM_RV32
        port map (
            clock   => clock,
            we      => we,
            address => address,
            datain  => datain,
            dataout => dataout_ram
        );

    uut_rom: component ROM_RV32
        port map (
            address => address,
            dataout => dataout_rom
        );

    -- Clock process
    clock_process: process
    begin
        while not test_finished loop
            clock <= '0';
            wait for 5 ns;
            clock <= '1';
            wait for 5 ns;
        end loop;
        wait;
    end process;

    -- Testbench stimulus process
    stimulus_process: process
    begin
        wait for 20 ns; -- Wait for initial stabilization

        -- RAM test: Write and read sequence
        for i in 0 to 255 loop
            -- Write operation
            we <= '1';
            address <= std_logic_vector(to_unsigned(i, 8));
            datain <= std_logic_vector(to_unsigned(i, 32));
            wait for 10 ns;
            
            -- Read operation
            we <= '0';
            address <= std_logic_vector(to_unsigned(i, 8));
            wait for 10 ns;
            
            -- Assertion to check if the read data matches the written data
            assert dataout_ram = std_logic_vector(to_unsigned(i, 32))
            report "RAM test failed at address " & integer'image(i)
            severity error;

            report "RAM test passed at address " & integer'image(i) severity note;
        
        end loop;

        -- ROM test: Read and verify contents
        for i in 0 to 255 loop
            address <= std_logic_vector(to_unsigned(i, 8));
            wait for 10 ns; -- Wait for the ROM to output the data

            -- Assertion to check if the ROM data matches the expected value
            assert dataout_rom = std_logic_vector(to_unsigned(i, 32))
            report "ROM test failed at address " & integer'image(i) & 
                " Expected: " & to_string(std_logic_vector(to_unsigned(i, 32))) & 
                " Got: " & to_string(dataout_rom)
            severity error;

            report "ROM test passed at address " & integer'image(i) severity note;

        end loop;
        
        test_finished <= true;
        wait; 
    end process;

end architecture behavior;

proj6/src/wave.vcd
$date
  Tue Dec  5 19:05:23 2023
$end
$version
  GHDL v0
$end
$timescale
  1 fs
$end
$scope module standard $end
$upscope $end
$scope module textio $end
$upscope $end
$scope module std_logic_1164 $end
$upscope $end
$scope module numeric_std $end
$upscope $end
$scope module testbench_ram_rom $end
$var reg 1 ! clock $end
$var reg 1 " we $end
$var reg 8 # address[7:0] $end
$var reg 32 $ datain[31:0] $end
$var reg 32 % dataout_ram[31:0] $end
$var reg 32 & dataout_rom[31:0] $end
$var reg 1 ' test_finished $end
$scope module uut_ram $end
$var reg 1 ( clock $end
$var reg 1 ) we $end
$var reg 8 * address[7:0] $end
$var reg 32 + datain[31:0] $end
$var reg 32 , dataout[31:0] $end
$comment mem is not handled $end
$var reg 8 - read_address[7:0] $end
$upscope $end
$scope module uut_rom $end
$var reg 8 . address[7:0] $end
$var reg 32 / dataout[31:0] $end
$comment mem is not handled $end
$upscope $end
$upscope $end
$enddefinitions $end
#0
0!
0"
b00000000 #
b00000000000000000000000000000000 $
bUUUUUUUUUUUUUUUUUUUUUUUUUUUUUUUU %
b00000000000000000000000000000000 &
0'
0(
0)
b00000000 *
b00000000000000000000000000000000 +
bUUUUUUUUUUUUUUUUUUUUUUUUUUUUUUUU ,
b00000000 -
b00000000 .
b00000000000000000000000000000000 /
#5000000
1!
1(
#10000000
0!
0(
#15000000
1!
1(
#20000000
0!
1"
0(
1)
#25000000
1!
b00000000000000000000000000000000 %
1(
b00000000000000000000000000000000 ,
#30000000
0!
0"
0(
0)
#35000000
1!
1(
#40000000
0!
1"
b00000001 #
b00000000000000000000000000000001 $
b00000000000000000000000000000001 &
0(
1)
b00000001 *
b00000000000000000000000000000001 +
b00000001 .
b00000000000000000000000000000001 /
#45000000
1!
1(
#50000000
0!
0"
0(
0)
#55000000
1!
b00000000000000000000000000000001 %
1(
b00000000000000000000000000000001 ,
b00000001 -
#60000000
0!
1"
b00000010 #
b00000000000000000000000000000010 $
b00000000000000000000000000000010 &
0(
1)
b00000010 *
b00000000000000000000000000000010 +
b00000010 .
b00000000000000000000000000000010 /
#65000000
1!
1(
#70000000
0!
0"
0(
0)
#75000000
1!
b00000000000000000000000000000010 %
1(
b00000000000000000000000000000010 ,
b00000010 -
#80000000
0!
1"
b00000011 #
b00000000000000000000000000000011 $
b00000000000000000000000000000011 &
0(
1)
b00000011 *
b00000000000000000000000000000011 +
b00000011 .
b00000000000000000000000000000011 /
#85000000
1!
1(
#90000000
0!
0"
0(
0)
#95000000
1!
b00000000000000000000000000000011 %
1(
b00000000000000000000000000000011 ,
b00000011 -
#100000000
0!
1"
b00000100 #
b00000000000000000000000000000100 $
b00000000000000000000000000000100 &
0(
1)
b00000100 *
b00000000000000000000000000000100 +
b00000100 .
b00000000000000000000000000000100 /
#105000000
1!
1(
#110000000
0!
0"
0(
0)
#115000000
1!
b00000000000000000000000000000100 %
1(
b00000000000000000000000000000100 ,
b00000100 -
#120000000
0!
1"
b00000101 #
b00000000000000000000000000000101 $
b00000000000000000000000000000101 &
0(
1)
b00000101 *
b00000000000000000000000000000101 +
b00000101 .
b00000000000000000000000000000101 /
#125000000
1!
1(
#130000000
0!
0"
0(
0)
#135000000
1!
b00000000000000000000000000000101 %
1(
b00000000000000000000000000000101 ,
b00000101 -
#140000000
0!
1"
b00000110 #
b00000000000000000000000000000110 $
b00000000000000000000000000000110 &
0(
1)
b00000110 *
b00000000000000000000000000000110 +
b00000110 .
b00000000000000000000000000000110 /
#145000000
1!
1(
#150000000
0!
0"
0(
0)
#155000000
1!
b00000000000000000000000000000110 %
1(
b00000000000000000000000000000110 ,
b00000110 -
#160000000
0!
1"
b00000111 #
b00000000000000000000000000000111 $
b00000000000000000000000000000111 &
0(
1)
b00000111 *
b00000000000000000000000000000111 +
b00000111 .
b00000000000000000000000000000111 /
#165000000
1!
1(
#170000000
0!
0"
0(
0)
#175000000
1!
b00000000000000000000000000000111 %
1(
b00000000000000000000000000000111 ,
b00000111 -
#180000000
0!
1"
b00001000 #
b00000000000000000000000000001000 $
b00000000000000000000000000001000 &
0(
1)
b00001000 *
b00000000000000000000000000001000 +
b00001000 .
b00000000000000000000000000001000 /
#185000000
1!
1(
#190000000
0!
0"
0(
0)
#195000000
1!
b00000000000000000000000000001000 %
1(
b00000000000000000000000000001000 ,
b00001000 -
#200000000
0!
1"
b00001001 #
b00000000000000000000000000001001 $
b00000000000000000000000000001001 &
0(
1)
b00001001 *
b00000000000000000000000000001001 +
b00001001 .
b00000000000000000000000000001001 /
#205000000
1!
1(
#210000000
0!
0"
0(
0)
#215000000
1!
b00000000000000000000000000001001 %
1(
b00000000000000000000000000001001 ,
b00001001 -
#220000000
0!
1"
b00001010 #
b00000000000000000000000000001010 $
b00000000000000000000000000001010 &
0(
1)
b00001010 *
b00000000000000000000000000001010 +
b00001010 .
b00000000000000000000000000001010 /
#225000000
1!
1(
#230000000
0!
0"
0(
0)
#235000000
1!
b00000000000000000000000000001010 %
1(
b00000000000000000000000000001010 ,
b00001010 -
#240000000
0!
1"
b00001011 #
b00000000000000000000000000001011 $
b00000000000000000000000000001011 &
0(
1)
b00001011 *
b00000000000000000000000000001011 +
b00001011 .
b00000000000000000000000000001011 /
#245000000
1!
1(
#250000000
0!
0"
0(
0)
#255000000
1!
b00000000000000000000000000001011 %
1(
b00000000000000000000000000001011 ,
b00001011 -
#260000000
0!
1"
b00001100 #
b00000000000000000000000000001100 $
b00000000000000000000000000001100 &
0(
1)
b00001100 *
b00000000000000000000000000001100 +
b00001100 .
b00000000000000000000000000001100 /
#265000000
1!
1(
#270000000
0!
0"
0(
0)
#275000000
1!
b00000000000000000000000000001100 %
1(
b00000000000000000000000000001100 ,
b00001100 -
#280000000
0!
1"
b00001101 #
b00000000000000000000000000001101 $
b00000000000000000000000000001101 &
0(
1)
b00001101 *
b00000000000000000000000000001101 +
b00001101 .
b00000000000000000000000000001101 /
#285000000
1!
1(
#290000000
0!
0"
0(
0)
#295000000
1!
b00000000000000000000000000001101 %
1(
b00000000000000000000000000001101 ,
b00001101 -
#300000000
0!
1"
b00001110 #
b00000000000000000000000000001110 $
b00000000000000000000000000001110 &
0(
1)
b00001110 *
b00000000000000000000000000001110 +
b00001110 .
b00000000000000000000000000001110 /
#305000000
1!
1(
#310000000
0!
0"
0(
0)
#315000000
1!
b00000000000000000000000000001110 %
1(
b00000000000000000000000000001110 ,
b00001110 -
#320000000
0!
1"
b00001111 #
b00000000000000000000000000001111 $
b00000000000000000000000000001111 &
0(
1)
b00001111 *
b00000000000000000000000000001111 +
b00001111 .
b00000000000000000000000000001111 /
#325000000
1!
1(
#330000000
0!
0"
0(
0)
#335000000
1!
b00000000000000000000000000001111 %
1(
b00000000000000000000000000001111 ,
b00001111 -
#340000000
0!
1"
b00010000 #
b00000000000000000000000000010000 $
b00000000000000000000000000010000 &
0(
1)
b00010000 *
b00000000000000000000000000010000 +
b00010000 .
b00000000000000000000000000010000 /
#345000000
1!
1(
#350000000
0!
0"
0(
0)
#355000000
1!
b00000000000000000000000000010000 %
1(
b00000000000000000000000000010000 ,
b00010000 -
#360000000
0!
1"
b00010001 #
b00000000000000000000000000010001 $
b00000000000000000000000000010001 &
0(
1)
b00010001 *
b00000000000000000000000000010001 +
b00010001 .
b00000000000000000000000000010001 /
#365000000
1!
1(
#370000000
0!
0"
0(
0)
#375000000
1!
b00000000000000000000000000010001 %
1(
b00000000000000000000000000010001 ,
b00010001 -
#380000000
0!
1"
b00010010 #
b00000000000000000000000000010010 $
b00000000000000000000000000010010 &
0(
1)
b00010010 *
b00000000000000000000000000010010 +
b00010010 .
b00000000000000000000000000010010 /
#385000000
1!
1(
#390000000
0!
0"
0(
0)
#395000000
1!
b00000000000000000000000000010010 %
1(
b00000000000000000000000000010010 ,
b00010010 -
#400000000
0!
1"
b00010011 #
b00000000000000000000000000010011 $
b00000000000000000000000000010011 &
0(
1)
b00010011 *
b00000000000000000000000000010011 +
b00010011 .
b00000000000000000000000000010011 /
#405000000
1!
1(
#410000000
0!
0"
0(
0)
#415000000
1!
b00000000000000000000000000010011 %
1(
b00000000000000000000000000010011 ,
b00010011 -
#420000000
0!
1"
b00010100 #
b00000000000000000000000000010100 $
b00000000000000000000000000010100 &
0(
1)
b00010100 *
b00000000000000000000000000010100 +
b00010100 .
b00000000000000000000000000010100 /
#425000000
1!
1(
#430000000
0!
0"
0(
0)
#435000000
1!
b00000000000000000000000000010100 %
1(
b00000000000000000000000000010100 ,
b00010100 -
#440000000
0!
1"
b00010101 #
b00000000000000000000000000010101 $
b00000000000000000000000000010101 &
0(
1)
b00010101 *
b00000000000000000000000000010101 +
b00010101 .
b00000000000000000000000000010101 /
#445000000
1!
1(
#450000000
0!
0"
0(
0)
#455000000
1!
b00000000000000000000000000010101 %
1(
b00000000000000000000000000010101 ,
b00010101 -
#460000000
0!
1"
b00010110 #
b00000000000000000000000000010110 $
b00000000000000000000000000010110 &
0(
1)
b00010110 *
b00000000000000000000000000010110 +
b00010110 .
b00000000000000000000000000010110 /
#465000000
1!
1(
#470000000
0!
0"
0(
0)
#475000000
1!
b00000000000000000000000000010110 %
1(
b00000000000000000000000000010110 ,
b00010110 -
#480000000
0!
1"
b00010111 #
b00000000000000000000000000010111 $
b00000000000000000000000000010111 &
0(
1)
b00010111 *
b00000000000000000000000000010111 +
b00010111 .
b00000000000000000000000000010111 /
#485000000
1!
1(
#490000000
0!
0"
0(
0)
#495000000
1!
b00000000000000000000000000010111 %
1(
b00000000000000000000000000010111 ,
b00010111 -
#500000000
0!
1"
b00011000 #
b00000000000000000000000000011000 $
b00000000000000000000000000011000 &
0(
1)
b00011000 *
b00000000000000000000000000011000 +
b00011000 .
b00000000000000000000000000011000 /
#505000000
1!
1(
#510000000
0!
0"
0(
0)
#515000000
1!
b00000000000000000000000000011000 %
1(
b00000000000000000000000000011000 ,
b00011000 -
#520000000
0!
1"
b00011001 #
b00000000000000000000000000011001 $
b00000000000000000000000000011001 &
0(
1)
b00011001 *
b00000000000000000000000000011001 +
b00011001 .
b00000000000000000000000000011001 /
#525000000
1!
1(
#530000000
0!
0"
0(
0)
#535000000
1!
b00000000000000000000000000011001 %
1(
b00000000000000000000000000011001 ,
b00011001 -
#540000000
0!
1"
b00011010 #
b00000000000000000000000000011010 $
b00000000000000000000000000011010 &
0(
1)
b00011010 *
b00000000000000000000000000011010 +
b00011010 .
b00000000000000000000000000011010 /
#545000000
1!
1(
#550000000
0!
0"
0(
0)
#555000000
1!
b00000000000000000000000000011010 %
1(
b00000000000000000000000000011010 ,
b00011010 -
#560000000
0!
1"
b00011011 #
b00000000000000000000000000011011 $
b00000000000000000000000000011011 &
0(
1)
b00011011 *
b00000000000000000000000000011011 +
b00011011 .
b00000000000000000000000000011011 /
#565000000
1!
1(
#570000000
0!
0"
0(
0)
#575000000
1!
b00000000000000000000000000011011 %
1(
b00000000000000000000000000011011 ,
b00011011 -
#580000000
0!
1"
b00011100 #
b00000000000000000000000000011100 $
b00000000000000000000000000011100 &
0(
1)
b00011100 *
b00000000000000000000000000011100 +
b00011100 .
b00000000000000000000000000011100 /
#585000000
1!
1(
#590000000
0!
0"
0(
0)
#595000000
1!
b00000000000000000000000000011100 %
1(
b00000000000000000000000000011100 ,
b00011100 -
#600000000
0!
1"
b00011101 #
b00000000000000000000000000011101 $
b00000000000000000000000000011101 &
0(
1)
b00011101 *
b00000000000000000000000000011101 +
b00011101 .
b00000000000000000000000000011101 /
#605000000
1!
1(
#610000000
0!
0"
0(
0)
#615000000
1!
b00000000000000000000000000011101 %
1(
b00000000000000000000000000011101 ,
b00011101 -
#620000000
0!
1"
b00011110 #
b00000000000000000000000000011110 $
b00000000000000000000000000011110 &
0(
1)
b00011110 *
b00000000000000000000000000011110 +
b00011110 .
b00000000000000000000000000011110 /
#625000000
1!
1(
#630000000
0!
0"
0(
0)
#635000000
1!
b00000000000000000000000000011110 %
1(
b00000000000000000000000000011110 ,
b00011110 -
#640000000
0!
1"
b00011111 #
b00000000000000000000000000011111 $
b00000000000000000000000000011111 &
0(
1)
b00011111 *
b00000000000000000000000000011111 +
b00011111 .
b00000000000000000000000000011111 /
#645000000
1!
1(
#650000000
0!
0"
0(
0)
#655000000
1!
b00000000000000000000000000011111 %
1(
b00000000000000000000000000011111 ,
b00011111 -
#660000000
0!
1"
b00100000 #
b00000000000000000000000000100000 $
b00000000000000000000000000100000 &
0(
1)
b00100000 *
b00000000000000000000000000100000 +
b00100000 .
b00000000000000000000000000100000 /
#665000000
1!
1(
#670000000
0!
0"
0(
0)
#675000000
1!
b00000000000000000000000000100000 %
1(
b00000000000000000000000000100000 ,
b00100000 -
#680000000
0!
1"
b00100001 #
b00000000000000000000000000100001 $
b00000000000000000000000000100001 &
0(
1)
b00100001 *
b00000000000000000000000000100001 +
b00100001 .
b00000000000000000000000000100001 /
#685000000
1!
1(
#690000000
0!
0"
0(
0)
#695000000
1!
b00000000000000000000000000100001 %
1(
b00000000000000000000000000100001 ,
b00100001 -
#700000000
0!
1"
b00100010 #
b00000000000000000000000000100010 $
b00000000000000000000000000100010 &
0(
1)
b00100010 *
b00000000000000000000000000100010 +
b00100010 .
b00000000000000000000000000100010 /
#705000000
1!
1(
#710000000
0!
0"
0(
0)
#715000000
1!
b00000000000000000000000000100010 %
1(
b00000000000000000000000000100010 ,
b00100010 -
#720000000
0!
1"
b00100011 #
b00000000000000000000000000100011 $
b00000000000000000000000000100011 &
0(
1)
b00100011 *
b00000000000000000000000000100011 +
b00100011 .
b00000000000000000000000000100011 /
#725000000
1!
1(
#730000000
0!
0"
0(
0)
#735000000
1!
b00000000000000000000000000100011 %
1(
b00000000000000000000000000100011 ,
b00100011 -
#740000000
0!
1"
b00100100 #
b00000000000000000000000000100100 $
b00000000000000000000000000100100 &
0(
1)
b00100100 *
b00000000000000000000000000100100 +
b00100100 .
b00000000000000000000000000100100 /
#745000000
1!
1(
#750000000
0!
0"
0(
0)
#755000000
1!
b00000000000000000000000000100100 %
1(
b00000000000000000000000000100100 ,
b00100100 -
#760000000
0!
1"
b00100101 #
b00000000000000000000000000100101 $
b00000000000000000000000000100101 &
0(
1)
b00100101 *
b00000000000000000000000000100101 +
b00100101 .
b00000000000000000000000000100101 /
#765000000
1!
1(
#770000000
0!
0"
0(
0)
#775000000
1!
b00000000000000000000000000100101 %
1(
b00000000000000000000000000100101 ,
b00100101 -
#780000000
0!
1"
b00100110 #
b00000000000000000000000000100110 $
b00000000000000000000000000100110 &
0(
1)
b00100110 *
b00000000000000000000000000100110 +
b00100110 .
b00000000000000000000000000100110 /
#785000000
1!
1(
#790000000
0!
0"
0(
0)
#795000000
1!
b00000000000000000000000000100110 %
1(
b00000000000000000000000000100110 ,
b00100110 -
#800000000
0!
1"
b00100111 #
b00000000000000000000000000100111 $
b00000000000000000000000000100111 &
0(
1)
b00100111 *
b00000000000000000000000000100111 +
b00100111 .
b00000000000000000000000000100111 /
#805000000
1!
1(
#810000000
0!
0"
0(
0)
#815000000
1!
b00000000000000000000000000100111 %
1(
b00000000000000000000000000100111 ,
b00100111 -
#820000000
0!
1"
b00101000 #
b00000000000000000000000000101000 $
b00000000000000000000000000101000 &
0(
1)
b00101000 *
b00000000000000000000000000101000 +
b00101000 .
b00000000000000000000000000101000 /
#825000000
1!
1(
#830000000
0!
0"
0(
0)
#835000000
1!
b00000000000000000000000000101000 %
1(
b00000000000000000000000000101000 ,
b00101000 -
#840000000
0!
1"
b00101001 #
b00000000000000000000000000101001 $
b00000000000000000000000000101001 &
0(
1)
b00101001 *
b00000000000000000000000000101001 +
b00101001 .
b00000000000000000000000000101001 /
#845000000
1!
1(
#850000000
0!
0"
0(
0)
#855000000
1!
b00000000000000000000000000101001 %
1(
b00000000000000000000000000101001 ,
b00101001 -
#860000000
0!
1"
b00101010 #
b00000000000000000000000000101010 $
b00000000000000000000000000101010 &
0(
1)
b00101010 *
b00000000000000000000000000101010 +
b00101010 .
b00000000000000000000000000101010 /
#865000000
1!
1(
#870000000
0!
0"
0(
0)
#875000000
1!
b00000000000000000000000000101010 %
1(
b00000000000000000000000000101010 ,
b00101010 -
#880000000
0!
1"
b00101011 #
b00000000000000000000000000101011 $
b00000000000000000000000000101011 &
0(
1)
b00101011 *
b00000000000000000000000000101011 +
b00101011 .
b00000000000000000000000000101011 /
#885000000
1!
1(
#890000000
0!
0"
0(
0)
#895000000
1!
b00000000000000000000000000101011 %
1(
b00000000000000000000000000101011 ,
b00101011 -
#900000000
0!
1"
b00101100 #
b00000000000000000000000000101100 $
b00000000000000000000000000101100 &
0(
1)
b00101100 *
b00000000000000000000000000101100 +
b00101100 .
b00000000000000000000000000101100 /
#905000000
1!
1(
#910000000
0!
0"
0(
0)
#915000000
1!
b00000000000000000000000000101100 %
1(
b00000000000000000000000000101100 ,
b00101100 -
#920000000
0!
1"
b00101101 #
b00000000000000000000000000101101 $
b00000000000000000000000000101101 &
0(
1)
b00101101 *
b00000000000000000000000000101101 +
b00101101 .
b00000000000000000000000000101101 /
#925000000
1!
1(
#930000000
0!
0"
0(
0)
#935000000
1!
b00000000000000000000000000101101 %
1(
b00000000000000000000000000101101 ,
b00101101 -
#940000000
0!
1"
b00101110 #
b00000000000000000000000000101110 $
b00000000000000000000000000101110 &
0(
1)
b00101110 *
b00000000000000000000000000101110 +
b00101110 .
b00000000000000000000000000101110 /
#945000000
1!
1(
#950000000
0!
0"
0(
0)
#955000000
1!
b00000000000000000000000000101110 %
1(
b00000000000000000000000000101110 ,
b00101110 -
#960000000
0!
1"
b00101111 #
b00000000000000000000000000101111 $
b00000000000000000000000000101111 &
0(
1)
b00101111 *
b00000000000000000000000000101111 +
b00101111 .
b00000000000000000000000000101111 /
#965000000
1!
1(
#970000000
0!
0"
0(
0)
#975000000
1!
b00000000000000000000000000101111 %
1(
b00000000000000000000000000101111 ,
b00101111 -
#980000000
0!
1"
b00110000 #
b00000000000000000000000000110000 $
b00000000000000000000000000110000 &
0(
1)
b00110000 *
b00000000000000000000000000110000 +
b00110000 .
b00000000000000000000000000110000 /
#985000000
1!
1(
#990000000
0!
0"
0(
0)
#995000000
1!
b00000000000000000000000000110000 %
1(
b00000000000000000000000000110000 ,
b00110000 -
#1000000000
0!
1"
b00110001 #
b00000000000000000000000000110001 $
b00000000000000000000000000110001 &
0(
1)
b00110001 *
b00000000000000000000000000110001 +
b00110001 .
b00000000000000000000000000110001 /
#1005000000
1!
1(
#1010000000
0!
0"
0(
0)
#1015000000
1!
b00000000000000000000000000110001 %
1(
b00000000000000000000000000110001 ,
b00110001 -
#1020000000
0!
1"
b00110010 #
b00000000000000000000000000110010 $
b00000000000000000000000000110010 &
0(
1)
b00110010 *
b00000000000000000000000000110010 +
b00110010 .
b00000000000000000000000000110010 /
#1025000000
1!
1(
#1030000000
0!
0"
0(
0)
#1035000000
1!
b00000000000000000000000000110010 %
1(
b00000000000000000000000000110010 ,
b00110010 -
#1040000000
0!
1"
b00110011 #
b00000000000000000000000000110011 $
b00000000000000000000000000110011 &
0(
1)
b00110011 *
b00000000000000000000000000110011 +
b00110011 .
b00000000000000000000000000110011 /
#1045000000
1!
1(
#1050000000
0!
0"
0(
0)
#1055000000
1!
b00000000000000000000000000110011 %
1(
b00000000000000000000000000110011 ,
b00110011 -
#1060000000
0!
1"
b00110100 #
b00000000000000000000000000110100 $
b00000000000000000000000000110100 &
0(
1)
b00110100 *
b00000000000000000000000000110100 +
b00110100 .
b00000000000000000000000000110100 /
#1065000000
1!
1(
#1070000000
0!
0"
0(
0)
#1075000000
1!
b00000000000000000000000000110100 %
1(
b00000000000000000000000000110100 ,
b00110100 -
#1080000000
0!
1"
b00110101 #
b00000000000000000000000000110101 $
b00000000000000000000000000110101 &
0(
1)
b00110101 *
b00000000000000000000000000110101 +
b00110101 .
b00000000000000000000000000110101 /
#1085000000
1!
1(
#1090000000
0!
0"
0(
0)
#1095000000
1!
b00000000000000000000000000110101 %
1(
b00000000000000000000000000110101 ,
b00110101 -
#1100000000
0!
1"
b00110110 #
b00000000000000000000000000110110 $
b00000000000000000000000000110110 &
0(
1)
b00110110 *
b00000000000000000000000000110110 +
b00110110 .
b00000000000000000000000000110110 /
#1105000000
1!
1(
#1110000000
0!
0"
0(
0)
#1115000000
1!
b00000000000000000000000000110110 %
1(
b00000000000000000000000000110110 ,
b00110110 -
#1120000000
0!
1"
b00110111 #
b00000000000000000000000000110111 $
b00000000000000000000000000110111 &
0(
1)
b00110111 *
b00000000000000000000000000110111 +
b00110111 .
b00000000000000000000000000110111 /
#1125000000
1!
1(
#1130000000
0!
0"
0(
0)
#1135000000
1!
b00000000000000000000000000110111 %
1(
b00000000000000000000000000110111 ,
b00110111 -
#1140000000
0!
1"
b00111000 #
b00000000000000000000000000111000 $
b00000000000000000000000000111000 &
0(
1)
b00111000 *
b00000000000000000000000000111000 +
b00111000 .
b00000000000000000000000000111000 /
#1145000000
1!
1(
#1150000000
0!
0"
0(
0)
#1155000000
1!
b00000000000000000000000000111000 %
1(
b00000000000000000000000000111000 ,
b00111000 -
#1160000000
0!
1"
b00111001 #
b00000000000000000000000000111001 $
b00000000000000000000000000111001 &
0(
1)
b00111001 *
b00000000000000000000000000111001 +
b00111001 .
b00000000000000000000000000111001 /
#1165000000
1!
1(
#1170000000
0!
0"
0(
0)
#1175000000
1!
b00000000000000000000000000111001 %
1(
b00000000000000000000000000111001 ,
b00111001 -
#1180000000
0!
1"
b00111010 #
b00000000000000000000000000111010 $
b00000000000000000000000000111010 &
0(
1)
b00111010 *
b00000000000000000000000000111010 +
b00111010 .
b00000000000000000000000000111010 /
#1185000000
1!
1(
#1190000000
0!
0"
0(
0)
#1195000000
1!
b00000000000000000000000000111010 %
1(
b00000000000000000000000000111010 ,
b00111010 -
#1200000000
0!
1"
b00111011 #
b00000000000000000000000000111011 $
b00000000000000000000000000111011 &
0(
1)
b00111011 *
b00000000000000000000000000111011 +
b00111011 .
b00000000000000000000000000111011 /
#1205000000
1!
1(
#1210000000
0!
0"
0(
0)
#1215000000
1!
b00000000000000000000000000111011 %
1(
b00000000000000000000000000111011 ,
b00111011 -
#1220000000
0!
1"
b00111100 #
b00000000000000000000000000111100 $
b00000000000000000000000000111100 &
0(
1)
b00111100 *
b00000000000000000000000000111100 +
b00111100 .
b00000000000000000000000000111100 /
#1225000000
1!
1(
#1230000000
0!
0"
0(
0)
#1235000000
1!
b00000000000000000000000000111100 %
1(
b00000000000000000000000000111100 ,
b00111100 -
#1240000000
0!
1"
b00111101 #
b00000000000000000000000000111101 $
b00000000000000000000000000111101 &
0(
1)
b00111101 *
b00000000000000000000000000111101 +
b00111101 .
b00000000000000000000000000111101 /
#1245000000
1!
1(
#1250000000
0!
0"
0(
0)
#1255000000
1!
b00000000000000000000000000111101 %
1(
b00000000000000000000000000111101 ,
b00111101 -
#1260000000
0!
1"
b00111110 #
b00000000000000000000000000111110 $
b00000000000000000000000000111110 &
0(
1)
b00111110 *
b00000000000000000000000000111110 +
b00111110 .
b00000000000000000000000000111110 /
#1265000000
1!
1(
#1270000000
0!
0"
0(
0)
#1275000000
1!
b00000000000000000000000000111110 %
1(
b00000000000000000000000000111110 ,
b00111110 -
#1280000000
0!
1"
b00111111 #
b00000000000000000000000000111111 $
b00000000000000000000000000111111 &
0(
1)
b00111111 *
b00000000000000000000000000111111 +
b00111111 .
b00000000000000000000000000111111 /
#1285000000
1!
1(
#1290000000
0!
0"
0(
0)
#1295000000
1!
b00000000000000000000000000111111 %
1(
b00000000000000000000000000111111 ,
b00111111 -
#1300000000
0!
1"
b01000000 #
b00000000000000000000000001000000 $
b00000000000000000000000001000000 &
0(
1)
b01000000 *
b00000000000000000000000001000000 +
b01000000 .
b00000000000000000000000001000000 /
#1305000000
1!
1(
#1310000000
0!
0"
0(
0)
#1315000000
1!
b00000000000000000000000001000000 %
1(
b00000000000000000000000001000000 ,
b01000000 -
#1320000000
0!
1"
b01000001 #
b00000000000000000000000001000001 $
b00000000000000000000000001000001 &
0(
1)
b01000001 *
b00000000000000000000000001000001 +
b01000001 .
b00000000000000000000000001000001 /
#1325000000
1!
1(
#1330000000
0!
0"
0(
0)
#1335000000
1!
b00000000000000000000000001000001 %
1(
b00000000000000000000000001000001 ,
b01000001 -
#1340000000
0!
1"
b01000010 #
b00000000000000000000000001000010 $
b00000000000000000000000001000010 &
0(
1)
b01000010 *
b00000000000000000000000001000010 +
b01000010 .
b00000000000000000000000001000010 /
#1345000000
1!
1(
#1350000000
0!
0"
0(
0)
#1355000000
1!
b00000000000000000000000001000010 %
1(
b00000000000000000000000001000010 ,
b01000010 -
#1360000000
0!
1"
b01000011 #
b00000000000000000000000001000011 $
b00000000000000000000000001000011 &
0(
1)
b01000011 *
b00000000000000000000000001000011 +
b01000011 .
b00000000000000000000000001000011 /
#1365000000
1!
1(
#1370000000
0!
0"
0(
0)
